django_sql_query_to_excel/__init__.py
test/__init__.py
test/test_main.py
django_sql_query_to_excel-1.0.0.dist-info/LICENSE
django_sql_query_to_excel-1.0.0.dist-info/METADATA
django_sql_query_to_excel-1.0.0.dist-info/WHEEL
django_sql_query_to_excel-1.0.0.dist-info/top_level.txt
django_sql_query_to_excel-1.0.0.dist-info/RECORD
