Metadata-Version: 2.1
Name: django-sql-query-to-excel
Version: 1.0.0
Summary: Converts Raw SQL Query to Excel Sheet
Home-page: https://tinker.com.np/
Author: Sunil Parajuli
Author-email: sunil.parajuli@tinker.com.np
License: GNU AGPL v3
Classifier: Environment :: Web Environment
Classifier: Framework :: Django
Classifier: Framework :: Django :: 3.0
Classifier: Intended Audience :: Developers
Classifier: License :: OSI Approved :: GNU Affero General Public License v3
Classifier: Operating System :: OS Independent
Classifier: Programming Language :: Python
Classifier: Programming Language :: Python :: 3.6
Classifier: Programming Language :: Python :: 3.7
License-File: LICENSE
Requires-Dist: django
Requires-Dist: XlsxWriter
